tcpw/__init__.py
tcpw/__main__.py
tcpw/tcpw
tcpw-0.1.10.dist-info/LICENSE
tcpw-0.1.10.dist-info/METADATA
tcpw-0.1.10.dist-info/WHEEL
tcpw-0.1.10.dist-info/entry_points.txt
tcpw-0.1.10.dist-info/top_level.txt
tcpw-0.1.10.dist-info/RECORD
