Metadata-Version: 2.1
Name: tcpw
Version: 0.1.10
Summary: Wait until TCP endpoints are open
Author-email: Andrii Kuzmin <jack.cvr@gmail.com>
Project-URL: Documentation, https://github.com/jackcvr/tcpw#readme
Project-URL: Issues, https://github.com/jackcvr/tcpw/issues
Project-URL: Source, https://github.com/jackcvr/tcpw
Keywords: wait-for-it,waitforit,tcp,expect,docker,containers
Classifier: Programming Language :: Python
Classifier: Programming Language :: Python :: 3
Requires-Python: >=3
License-File: LICENSE
Provides-Extra: dev
Requires-Dist: build ; extra == 'dev'
Requires-Dist: twine ; extra == 'dev'
